{"intensity":295,"laneId":1182343623,"dateObserved":"2025-02-28T00:00:00/2025-03-01T00:00:00","location":{"coordinates":[3.8837306666666667,43.5969973],"type":"Point"},"id":"MMM_EcoCompt_ED223110497_202502280000","type":"TrafficFlowObserved","vehicleType":"bicycle","reversedLane":false}
{"intensity":147,"laneId":1182343623,"dateObserved":"2025-03-01T00:00:00/2025-03-02T00:00:00","location":{"coordinates":[3.8837306666666667,43.5969973],"type":"Point"},"id":"MMM_EcoCompt_ED223110497_202503010000","type":"TrafficFlowObserved","vehicleType":"bicycle","reversedLane":false}
{"intensity":306,"laneId":1182343623,"dateObserved":"2025-02-20T00:00:00/2025-02-21T00:00:00","location":{"coordinates":[3.8837306666666667,43.5969973],"type":"Point"},"id":"MMM_EcoCompt_ED223110497_202502200000","type":"TrafficFlowObserved","vehicleType":"bicycle","reversedLane":false}
{"intensity":38,"laneId":1182343623,"dateObserved":"2025-02-22T00:00:00/2025-02-23T00:00:00","location":{"coordinates":[3.8837306666666667,43.5969973],"type":"Point"},"id":"MMM_EcoCompt_ED223110497_202502220000","type":"TrafficFlowObserved","vehicleType":"bicycle","reversedLane":false}
{"intensity":390,"laneId":1182343623,"dateObserved":"2025-02-26T00:00:00/2025-02-27T00:00:00","location":{"coordinates":[3.8837306666666667,43.5969973],"type":"Point"},"id":"MMM_EcoCompt_ED223110497_202502260000","type":"TrafficFlowObserved","vehicleType":"bicycle","reversedLane":false}
{"intensity":426,"laneId":1182343623,"dateObserved":"2025-03-03T00:00:00/2025-03-04T00:00:00","location":{"coordinates":[3.8837306666666667,43.5969973],"type":"Point"},"id":"MMM_EcoCompt_ED223110497_202503030000","type":"TrafficFlowObserved","vehicleType":"bicycle","reversedLane":false}
{"intensity":256,"laneId":1182343623,"dateObserved":"2025-02-21T00:00:00/2025-02-22T00:00:00","location":{"coordinates":[3.8837306666666667,43.5969973],"type":"Point"},"id":"MMM_EcoCompt_ED223110497_202502210000","type":"TrafficFlowObserved","vehicleType":"bicycle","reversedLane":false}
{"intensity":229,"laneId":1182343623,"dateObserved":"2025-03-02T00:00:00/2025-03-03T00:00:00","location":{"coordinates":[3.8837306666666667,43.5969973],"type":"Point"},"id":"MMM_EcoCompt_ED223110497_202503020000","type":"TrafficFlowObserved","vehicleType":"bicycle","reversedLane":false}
{"intensity":349,"laneId":1182343623,"dateObserved":"2025-02-27T00:00:00/2025-02-28T00:00:00","location":{"coordinates":[3.8837306666666667,43.5969973],"type":"Point"},"id":"MMM_EcoCompt_ED223110497_202502270000","type":"TrafficFlowObserved","vehicleType":"bicycle","reversedLane":false}
{"intensity":286,"laneId":1182343623,"dateObserved":"2025-02-19T00:00:00/2025-02-20T00:00:00","location":{"coordinates":[3.8837306666666667,43.5969973],"type":"Point"},"id":"MMM_EcoCompt_ED223110497_202502190000","type":"TrafficFlowObserved","vehicleType":"bicycle","reversedLane":false}
{"intensity":315,"laneId":1182343623,"dateObserved":"2025-02-24T00:00:00/2025-02-25T00:00:00","location":{"coordinates":[3.8837306666666667,43.5969973],"type":"Point"},"id":"MMM_EcoCompt_ED223110497_202502240000","type":"TrafficFlowObserved","vehicleType":"bicycle","reversedLane":false}
{"intensity":337,"laneId":1182343623,"dateObserved":"2025-02-25T00:00:00/2025-02-26T00:00:00","location":{"coordinates":[3.8837306666666667,43.5969973],"type":"Point"},"id":"MMM_EcoCompt_ED223110497_202502250000","type":"TrafficFlowObserved","vehicleType":"bicycle","reversedLane":false}
{"intensity":112,"laneId":1182343623,"dateObserved":"2025-02-23T00:00:00/2025-02-24T00:00:00","location":{"coordinates":[3.8837306666666667,43.5969973],"type":"Point"},"id":"MMM_EcoCompt_ED223110497_202502230000","type":"TrafficFlowObserved","vehicleType":"bicycle","reversedLane":false}
{"intensity":264,"laneId":1182343623,"dateObserved":"2025-03-04T00:00:00/2025-03-05T00:00:00","location":{"coordinates":[3.8837306666666667,43.5969973],"type":"Point"},"id":"MMM_EcoCompt_ED223110497_202503040000","type":"TrafficFlowObserved","vehicleType":"bicycle","reversedLane":false}
